xarray_accessors/__init__.py
xarray_accessors-0.1.0.dist-info/LICENSE
xarray_accessors-0.1.0.dist-info/WHEEL
xarray_accessors-0.1.0.dist-info/METADATA
xarray_accessors-0.1.0.dist-info/RECORD
