Metadata-Version: 2.1
Name: xarray-accessors
Version: 0.1.0
Summary: xarray extension for dataarray accessors
Home-page: https://github.com/astropenguin/xarray-accessors/
License: MIT
Author: Akio Taniguchi
Author-email: taniguchi@a.phys.nagoya-u.ac.jp
Requires-Python: >=3.6,<4.0
Classifier: License :: OSI Approved :: MIT License
Classifier: Programming Language :: Python :: 3
Classifier: Programming Language :: Python :: 3.6
Classifier: Programming Language :: Python :: 3.7
Classifier: Programming Language :: Python :: 3.8
Project-URL: Documentation, https://astropenguin.github.io/xarray-accessors/
